{
  "m_GameObject": {
    "m_FileID": 0,
    "m_PathID": 1356748341777045394
  },
  "m_Enabled": 1,
  "m_Script": {
    "m_FileID": 0,
    "m_PathID": 6240611404226988587
  },
  "m_Name": "",
  "animationObjects": [
    {
      "group": [
        {
          "m_FileID": 0,
          "m_PathID": -5420326227435339173
        },
        {
          "m_FileID": 0,
          "m_PathID": 1445824281670399655
        },
        {
          "m_FileID": 0,
          "m_PathID": -5246731489795187506
        }
      ],
      "startScale": 1.0,
      "scaleWeight": 1.2,
      "isAllScale": 0
    }
  ],
  "scrollAnimations": [],
  "rotationAnimations": []
}